pyoklock/clocks.py
pyoklock/google_calender.py
pyoklock/main.py
pyoklock-0.0.6.dist-info/LICENSE.txt
pyoklock-0.0.6.dist-info/METADATA
pyoklock-0.0.6.dist-info/WHEEL
pyoklock-0.0.6.dist-info/entry_points.txt
pyoklock-0.0.6.dist-info/top_level.txt
pyoklock-0.0.6.dist-info/RECORD
