Metadata-Version: 2.1
Name: pyoklock
Version: 0.0.6
Summary: python cli digital clock.
Home-page: https://github.com/6syun9/pyoklock
Author: vaaaaanquish
Author-email: 6syun9@gmail.com
License: MIT
Platform: any
Requires-Dist: prompt-toolkit
Requires-Dist: google-api-python-client
Requires-Dist: google-auth-httplib2
Requires-Dist: google-auth-oauthlib
